skyant/grpc/__init__.py
skyant/grpc/_client.py
skyant/grpc/_server.py
skyant_grpc-0.0.1.dist-info/LICENSE
skyant_grpc-0.0.1.dist-info/METADATA
skyant_grpc-0.0.1.dist-info/WHEEL
skyant_grpc-0.0.1.dist-info/top_level.txt
skyant_grpc-0.0.1.dist-info/RECORD
