Metadata-Version: 2.1
Name: skyant-grpc
Version: 0.0.1
Summary: Base objects to make gRPC client-server application
Home-page: https://skyant.dev
Author: Iurii Tarasenko
Author-email: info@skyant.dev
License: MIT
Project-URL: Source & issues, https://gitlab.com/skyant/python/grpc
Project-URL: Documentation, https://docs.skyant.dev/projects/shell
Keywords: pydantic,api,grpc,GCP
Classifier: Programming Language :: Python :: 3.10
Classifier: Intended Audience :: Developers
Classifier: Intended Audience :: Information Technology
Classifier: Topic :: Software Development :: Libraries :: Python Modules
Requires-Python: >=3.10
License-File: LICENSE
Requires-Dist: grpcio
Requires-Dist: grpcio-reflection
Requires-Dist: pydantic
